a0_baas_sdk/__init__.py
a0_baas_sdk/file.py
a0_baas_sdk/redis.py
a0_baas_sdk/remote/__init__.py
a0_baas_sdk/remote/auth.py
a0_baas_sdk/remote/config.py
a0_baas_sdk/remote/const.py
a0_baas_sdk/remote/file_api.py
a0_baas_sdk/remote/redis_api.py
a0_baas_sdk/remote/utils.py
marscode_baas_sdk/__init__.py
marscode_baas_sdk/file.py
marscode_baas_sdk/redis.py
marscode_baas_sdk/remote/__init__.py
marscode_baas_sdk/remote/auth.py
marscode_baas_sdk/remote/config.py
marscode_baas_sdk/remote/const.py
marscode_baas_sdk/remote/file_api.py
marscode_baas_sdk/remote/redis_api.py
marscode_baas_sdk/remote/utils.py
a0_baas_sdk-0.1.0a12.dist-info/LICENSE
a0_baas_sdk-0.1.0a12.dist-info/METADATA
a0_baas_sdk-0.1.0a12.dist-info/NOTICE
a0_baas_sdk-0.1.0a12.dist-info/WHEEL
a0_baas_sdk-0.1.0a12.dist-info/top_level.txt
a0_baas_sdk-0.1.0a12.dist-info/RECORD
